tenshi/__init__.py
tenshi-0.1.1.dist-info/licenses/LICENSE
tenshi-0.1.1.dist-info/METADATA
tenshi-0.1.1.dist-info/WHEEL
tenshi-0.1.1.dist-info/top_level.txt
tenshi-0.1.1.dist-info/RECORD
