Metadata-Version: 2.4
Name: tenshi
Version: 0.1.1
Summary: A Gemini AI wrapper with API key rotation and system prompt support.
Home-page: https://pypi.org/project/tenshi/
Author: RUBIN EXE
Classifier: Programming Language :: Python :: 3
Classifier: License :: OSI Approved :: MIT License
Classifier: Operating System :: OS Independent
Requires-Python: >=3.7
License-File: LICENSE
Requires-Dist: requests
Dynamic: author
Dynamic: classifier
Dynamic: description
Dynamic: description-content-type
Dynamic: home-page
Dynamic: license-file
Dynamic: requires-dist
Dynamic: requires-python
Dynamic: summary
